controlled_vocabulary_utils/__init__.py
controlled_vocabulary_utils/console_helper.py
controlled_vocabulary_utils/constants.py
controlled_vocabulary_utils/file_utils.py
controlled_vocabulary_utils/manager.py
controlled_vocabulary_utils/system_caller.py
controlled_vocabulary_utils-0.3.0.dist-info/AUTHORS.rst
controlled_vocabulary_utils-0.3.0.dist-info/METADATA
controlled_vocabulary_utils-0.3.0.dist-info/WHEEL
controlled_vocabulary_utils-0.3.0.dist-info/entry_points.txt
controlled_vocabulary_utils-0.3.0.dist-info/top_level.txt
controlled_vocabulary_utils-0.3.0.dist-info/RECORD
