Metadata-Version: 2.2
Name: controlled_vocabulary_utils
Version: 0.3.0
Summary: A package for evaluating values for terms in a controlled vocabulary.
Home-page: https://github.com/jai-python3/controlled-vocabulary-utils
Author: Jaideep Sundaram
Author-email: jai.python3@gmail.com
Keywords: controlled_vocabulary_utils
Classifier: Development Status :: 2 - Pre-Alpha
Classifier: Intended Audience :: Developers
Classifier: Natural Language :: English
Classifier: Programming Language :: Python :: 3.12
Requires-Python: >=3.10
License-File: AUTHORS.rst
Requires-Dist: Click>=7.0
Requires-Dist: PyYAML
Requires-Dist: Rich
Requires-Dist: singleton-decorator
Dynamic: author
Dynamic: author-email
Dynamic: classifier
Dynamic: description
Dynamic: home-page
Dynamic: keywords
Dynamic: requires-dist
Dynamic: requires-python
Dynamic: summary
